mcp_server_docker/__init__.py
mcp_server_docker/http_server.py
mcp_server_docker/input_schemas.py
mcp_server_docker/output_schemas.py
mcp_server_docker/server.py
mcp_server_docker/settings.py
cgx_mcp_server_docker-0.3.0.dist-info/METADATA
cgx_mcp_server_docker-0.3.0.dist-info/WHEEL
cgx_mcp_server_docker-0.3.0.dist-info/entry_points.txt
cgx_mcp_server_docker-0.3.0.dist-info/licenses/LICENSE
cgx_mcp_server_docker-0.3.0.dist-info/RECORD
