Metadata-Version: 2.4
Name: cgx-mcp-server-docker
Version: 0.3.0
Summary: A Docker MCP Server with enhanced session management and streamable-http support
Project-URL: Repository, https://github.com/ckreiling/mcp-server-docker
Project-URL: Issues, https://github.com/ckreiling/mcp-server-docker/issues
Project-URL: Documentation, https://github.com/ckreiling/mcp-server-docker/blob/main/README.md
Author-email: Christian Kreiling <kreiling@hey.com>
License:                     GNU GENERAL PUBLIC LICENSE
License-File: LICENSE
Keywords: agno,docker,mcp,model-context-protocol,server,streamable-http
Classifier: Development Status :: 4 - Beta
Classifier: Intended Audience :: Developers
Classifier: License :: OSI Approved :: MIT License
Classifier: Operating System :: OS Independent
Classifier: Programming Language :: Python :: 3
Classifier: Programming Language :: Python :: 3.12
Classifier: Topic :: Software Development :: Libraries :: Python Modules
Classifier: Topic :: System :: Systems Administration
Requires-Python: >=3.12
Requires-Dist: docker>=7.1.0
Requires-Dist: mcp>=1.1.0
Requires-Dist: paramiko>=3.5.1
Requires-Dist: pydantic-settings>=2.6.1
Requires-Dist: starlette>=0.41.3
Requires-Dist: uvicorn>=0.32.1
